{
	"credit": "Made with Blockbench",
	"textures": {
		"tray_bottom": "farmersdelight:block/tray_bottom",
		"particle": "largemeals:block/tray_omurice_leftover",
		"tray_omurice_leftover": "largemeals:block/tray_omurice_leftover"
	},
	"elements": [
		{
			"name": "plate",
			"from": [1, 0, 1],
			"to": [15, 2, 15],
			"faces": {
				"north": {"uv": [1, 11, 15, 13], "texture": "#tray_bottom"},
				"east": {"uv": [1, 11, 15, 13], "texture": "#tray_bottom"},
				"south": {"uv": [1, 11, 15, 13], "texture": "#tray_bottom"},
				"west": {"uv": [1, 11, 15, 13], "texture": "#tray_bottom"},
				"up": {"uv": [1, 1, 15, 15], "texture": "#tray_omurice_leftover"},
				"down": {"uv": [1, 1, 15, 15], "texture": "#tray_bottom", "cullface": "down"}
			}
		}
	],
	"groups": [
		{
			"name": "plate",
			"origin": [8, 8, 8],
			"color": 0,
			"children": [0]
		}
	]
}